{
    "1601222499": {
        "name": "EV Zug v ZSC Lions",
        "markets": [
            {
                "description": "moneyline",
                "prices": [
                    {
                        "designation": "home",
                        "price": -131
                    },
                    {
                        "designation": "away",
                        "price": 108
                    }
                ],
                "limit": 125
            }
        ]
    },
    "1601222500": {
        "name": "HC Lausanne v HC Davos",
        "markets": [
            {
                "description": "moneyline",
                "prices": [
                    {
                        "designation": "home",
                        "price": -122
                    },
                    {
                        "designation": "away",
                        "price": 101
                    }
                ],
                "limit": 125
            }
        ]
    },
    "1601263872": {
        "name": "SCL Tigers v HC Ambri-Piotta",
        "markets": [
            {
                "description": "moneyline",
                "prices": [
                    {
                        "designation": "home",
                        "price": -126
                    },
                    {
                        "designation": "away",
                        "price": 104
                    }
                ],
                "limit": 50
            }
        ]
    },
    "1601263880": {
        "name": "HC Ajoie v HC Lugano",
        "markets": [
            {
                "description": "moneyline",
                "prices": [
                    {
                        "designation": "home",
                        "price": 170
                    },
                    {
                        "designation": "away",
                        "price": -215
                    }
                ],
                "limit": 50
            }
        ]
    },
    "1601263875": {
        "name": "Rapperswil-Jona Lakers v Geneve-Servette HC",
        "markets": [
            {
                "description": "moneyline",
                "prices": [
                    {
                        "designation": "home",
                        "price": -116
                    },
                    {
                        "designation": "away",
                        "price": -105
                    }
                ],
                "limit": 50
            }
        ]
    },
    "1601263879": {
        "name": "EHC Biel v SC Bern",
        "markets": [
            {
                "description": "moneyline",
                "prices": [
                    {
                        "designation": "home",
                        "price": -107
                    },
                    {
                        "designation": "away",
                        "price": -114
                    }
                ],
                "limit": 50
            }
        ]
    }
}